ctao_cr_spectra/__init__.py
ctao_cr_spectra/_version.py
ctao_cr_spectra/definitions.py
ctao_cr_spectra/spectral.py
ctao_cr_spectra/version.py
ctao_cr_spectra/resources/dampe_p+he_2019.ecsv
ctao_cr_spectra/resources/dampe_p+he_2021.ecsv
ctao_cr_spectra/tests/__init__.py
ctao_cr_spectra/tests/test_definitions.py
ctao_cr_spectra/tests/test_spectral.py
ctao_cr_spectra/tests/test_version.py
ctao_dpps_cosmic_ray_spectra-0.1.1.dist-info/LICENSE
ctao_dpps_cosmic_ray_spectra-0.1.1.dist-info/METADATA
ctao_dpps_cosmic_ray_spectra-0.1.1.dist-info/WHEEL
ctao_dpps_cosmic_ray_spectra-0.1.1.dist-info/top_level.txt
ctao_dpps_cosmic_ray_spectra-0.1.1.dist-info/RECORD
